python3/__init__.py
python3/__main__.py
python3_alias-1.0.3.dist-info/LICENSE
python3_alias-1.0.3.dist-info/METADATA
python3_alias-1.0.3.dist-info/WHEEL
python3_alias-1.0.3.dist-info/entry_points.txt
python3_alias-1.0.3.dist-info/RECORD
