Metadata-Version: 2.1
Name: python3-alias
Version: 1.0.3
Summary: Hack to deal with a missing python3 alias on Windows
Home-page: https://github.com/matthewdeanmartin/python3
License: MIT
Keywords: python3,alias
Author: Matthew Martin
Author-email: matthewdeanmartin@gmail.com
Requires-Python: >=3.8
Classifier: Development Status :: 5 - Production/Stable
Classifier: License :: OSI Approved :: MIT License
Classifier: Operating System :: OS Independent
Classifier: Programming Language :: Python
Classifier: Programming Language :: Python :: 3
Classifier: Programming Language :: Python :: 3.8
Classifier: Programming Language :: Python :: 3.9
Classifier: Programming Language :: Python :: 3.10
Classifier: Programming Language :: Python :: 3.11
Classifier: Programming Language :: Python :: 3.12
Classifier: Programming Language :: Python :: 3.13
Project-URL: Bug Tracker, https://github.com/matthewdeanmartin/python3/issues
Project-URL: Change Log, https://github.com/matthewdeanmartin/python3/blob/main/CHANGELOG.md
Project-URL: Documentation, https://github.com/matthewdeanmartin/python3
Project-URL: Repository, https://github.com/matthewdeanmartin/python3
